pyvan.py
pyvan-1.2.3.dist-info/LICENSE
pyvan-1.2.3.dist-info/METADATA
pyvan-1.2.3.dist-info/WHEEL
pyvan-1.2.3.dist-info/entry_points.txt
pyvan-1.2.3.dist-info/top_level.txt
pyvan-1.2.3.dist-info/RECORD
