Metadata-Version: 2.1
Name: pyvan
Version: 1.2.3
Summary: Make runnable desktop apps from your python scripts more easily with pyvan!
Home-page: https://github.com/ClimenteA/pyvan
Author: Climente Alin
Author-email: climente.alin@gmail.com
License: MIT
License-File: LICENSE
Requires-Dist: click
Requires-Dist: gen-exe
Requires-Dist: pipreqs
Requires-Dist: requests
